[
  {
    "event_type": "deployment",
    "deployment_id": 3613543219,
    "repo_owner": "hrishi-york",
    "repo_name": "remote_exmpl",
    "environment": "github-pages",
    "ref": "another",
    "commit_sha": "666b7ea56a938201b66aaf2c5785e088733cdf10",
    "deployment_created_at": "2026-01-12T09:43:35Z",
    "status": "success",
    "status_created_at": "2026-01-12T09:43:56Z",
    "performed_via": "github-pages",
    "creator": "hrishi-york",
    "ingested_at": "2026-01-14T09:20:56.979763+00:00"
  },
  {
    "event_type": "deployment",
    "deployment_id": 3613357663,
    "repo_owner": "hrishi-york",
    "repo_name": "remote_exmpl",
    "environment": "github-pages",
    "ref": "another",
    "commit_sha": "43c50911c0e17df97a108118beed87fc7c21b9e9",
    "deployment_created_at": "2026-01-12T09:10:56Z",
    "status": "inactive",
    "status_created_at": "2026-01-12T09:43:56Z",
    "performed_via": "github-pages",
    "creator": "hrishi-york",
    "ingested_at": "2026-01-14T09:20:57.259025+00:00"
  },
  {
    "event_type": "deployment",
    "deployment_id": 3613138899,
    "repo_owner": "hrishi-york",
    "repo_name": "remote_exmpl",
    "environment": "github-pages",
    "ref": "main",
    "commit_sha": "eaf475318b93588a3a744c4ee84f519c929cd470",
    "deployment_created_at": "2026-01-12T08:26:52Z",
    "status": "inactive",
    "status_created_at": "2026-01-12T09:11:14Z",
    "performed_via": "github-pages",
    "creator": "hrishi-york",
    "ingested_at": "2026-01-14T09:20:57.535343+00:00"
  },
  {
    "event_type": "deployment",
    "deployment_id": 3620691061,
    "repo_owner": "hrishi-york",
    "repo_name": "Netlify_Deployment",
    "environment": "production",
    "ref": "main",
    "commit_sha": "e6b2786da541728e86eab8e872d7088cfba8204c",
    "deployment_created_at": "2026-01-13T09:17:20Z",
    "status": "success",
    "status_created_at": "2026-01-13T09:17:28Z",
    "performed_via": "github-actions",
    "creator": "hrishi-york",
    "ingested_at": "2026-01-14T09:20:58.849690+00:00"
  },
  {
    "event_type": "deployment",
    "deployment_id": 3620691057,
    "repo_owner": "hrishi-york",
    "repo_name": "Netlify_Deployment",
    "environment": "production",
    "ref": "main",
    "commit_sha": "e6b2786da541728e86eab8e872d7088cfba8204c",
    "deployment_created_at": "2026-01-13T09:17:20Z",
    "status": "failure",
    "status_created_at": "2026-01-13T09:17:27Z",
    "performed_via": "github-actions",
    "creator": "hrishi-york",
    "ingested_at": "2026-01-14T09:20:59.134298+00:00"
  },
  {
    "event_type": "deployment",
    "deployment_id": 3620644998,
    "repo_owner": "hrishi-york",
    "repo_name": "Netlify_Deployment",
    "environment": "production",
    "ref": "main",
    "commit_sha": "7f01b9a310f8da7257c1be7499d3ad32e0851923",
    "deployment_created_at": "2026-01-13T09:09:51Z",
    "status": "failure",
    "status_created_at": "2026-01-13T09:09:58Z",
    "performed_via": "github-actions",
    "creator": "hrishi-york",
    "ingested_at": "2026-01-14T09:20:59.398384+00:00"
  },
  {
    "event_type": "deployment",
    "deployment_id": 3620634004,
    "repo_owner": "hrishi-york",
    "repo_name": "Netlify_Deployment",
    "environment": "production",
    "ref": "main",
    "commit_sha": "addcb39a631738fe4854c1cfbe78e78df74b42f7",
    "deployment_created_at": "2026-01-13T09:08:01Z",
    "status": "failure",
    "status_created_at": "2026-01-13T09:08:07Z",
    "performed_via": "github-actions",
    "creator": "hrishi-york",
    "ingested_at": "2026-01-14T09:20:59.664573+00:00"
  },
  {
    "event_type": "deployment",
    "deployment_id": 3620564235,
    "repo_owner": "hrishi-york",
    "repo_name": "Netlify_Deployment",
    "environment": "production",
    "ref": "main",
    "commit_sha": "bb32e82f8fcefab63e972df63c52b5b36bda22db",
    "deployment_created_at": "2026-01-13T08:56:03Z",
    "status": "failure",
    "status_created_at": "2026-01-13T08:56:11Z",
    "performed_via": "github-actions",
    "creator": "hrishi-york",
    "ingested_at": "2026-01-14T09:20:59.936511+00:00"
  },
  {
    "event_type": "deployment",
    "deployment_id": 3620518625,
    "repo_owner": "hrishi-york",
    "repo_name": "Netlify_Deployment",
    "environment": "production",
    "ref": "main",
    "commit_sha": "b17f30d74d26afb08c02ca13d335d1f98e0776b6",
    "deployment_created_at": "2026-01-13T08:47:52Z",
    "status": "failure",
    "status_created_at": "2026-01-13T08:47:59Z",
    "performed_via": "github-actions",
    "creator": "hrishi-york",
    "ingested_at": "2026-01-14T09:21:00.227700+00:00"
  },
  {
    "event_type": "deployment",
    "deployment_id": 3620511094,
    "repo_owner": "hrishi-york",
    "repo_name": "Netlify_Deployment",
    "environment": "production",
    "ref": "main",
    "commit_sha": "cedc5cad79b634f037ec40b7ec774c981fc3a93e",
    "deployment_created_at": "2026-01-13T08:46:29Z",
    "status": "failure",
    "status_created_at": "2026-01-13T08:46:36Z",
    "performed_via": "github-actions",
    "creator": "hrishi-york",
    "ingested_at": "2026-01-14T09:21:00.521810+00:00"
  },
  {
    "event_type": "deployment",
    "deployment_id": 3620484527,
    "repo_owner": "hrishi-york",
    "repo_name": "Netlify_Deployment",
    "environment": "production",
    "ref": "main",
    "commit_sha": "fd9e6be11292c90e51fbece9ae0c24232a428345",
    "deployment_created_at": "2026-01-13T08:41:44Z",
    "status": "failure",
    "status_created_at": "2026-01-13T08:41:51Z",
    "performed_via": "github-actions",
    "creator": "hrishi-york",
    "ingested_at": "2026-01-14T09:21:00.788517+00:00"
  },
  {
    "event_type": "deployment",
    "deployment_id": 3620048202,
    "repo_owner": "hrishi-york",
    "repo_name": "Netlify_Deployment",
    "environment": "production",
    "ref": "main",
    "commit_sha": "a7e9df5d095b2022c4b99e2d7196e840a2322863",
    "deployment_created_at": "2026-01-13T07:10:59Z",
    "status": "failure",
    "status_created_at": "2026-01-13T07:11:04Z",
    "performed_via": "github-actions",
    "creator": "hrishi-york",
    "ingested_at": "2026-01-14T09:21:01.097656+00:00"
  },
  {
    "event_type": "deployment",
    "deployment_id": 3620043975,
    "repo_owner": "hrishi-york",
    "repo_name": "Netlify_Deployment",
    "environment": "production",
    "ref": "main",
    "commit_sha": "d04fbf29f86ca258298437b75ec9a5049e0a0600",
    "deployment_created_at": "2026-01-13T07:10:05Z",
    "status": "failure",
    "status_created_at": "2026-01-13T07:10:11Z",
    "performed_via": "github-actions",
    "creator": "hrishi-york",
    "ingested_at": "2026-01-14T09:21:01.362339+00:00"
  },
  {
    "event_type": "deployment",
    "deployment_id": 3620026729,
    "repo_owner": "hrishi-york",
    "repo_name": "Netlify_Deployment",
    "environment": "production",
    "ref": "main",
    "commit_sha": "a7e9df5d095b2022c4b99e2d7196e840a2322863",
    "deployment_created_at": "2026-01-13T07:06:16Z",
    "status": "failure",
    "status_created_at": "2026-01-13T07:06:21Z",
    "performed_via": "github-actions",
    "creator": "hrishi-york",
    "ingested_at": "2026-01-14T09:21:01.636552+00:00"
  },
  {
    "event_type": "deployment",
    "deployment_id": 3635898504,
    "repo_owner": "hrishi-york",
    "repo_name": "experimental_1",
    "environment": "github-pages",
    "ref": "main",
    "commit_sha": "b25697bd19987861546a661503c54c71dbd74bbc",
    "deployment_created_at": "2026-01-15T10:20:52Z",
    "status": "success",
    "status_created_at": "2026-01-15T10:21:10Z",
    "performed_via": "github-actions",
    "creator": "hrishi-york",
    "ingested_at": "2026-01-15T10:29:04.937579+00:00"
  },
  {
    "event_type": "deployment",
    "deployment_id": 3636035013,
    "repo_owner": "hrishi-york",
    "repo_name": "experimental_1",
    "environment": "github-pages",
    "ref": "main",
    "commit_sha": "3567a64ed3f58a356adce316d2704ff79f9f3966",
    "deployment_created_at": "2026-01-15T10:45:02Z",
    "status": "success",
    "status_created_at": "2026-01-15T10:45:18Z",
    "performed_via": "github-actions",
    "creator": "hrishi-york",
    "ingested_at": "2026-01-15T10:47:10.691601+00:00"
  },
  {
    "event_type": "deployment",
    "deployment_id": 3642783277,
    "repo_owner": "hrishi-york",
    "repo_name": "experimental_1",
    "environment": "github-pages",
    "ref": "main",
    "commit_sha": "92a2998e475b517b09a79c579b912e74065c5e0a",
    "deployment_created_at": "2026-01-16T09:21:58Z",
    "status": "success",
    "status_created_at": "2026-01-16T09:22:14Z",
    "performed_via": "github-actions",
    "creator": "hrishi-york",
    "ingested_at": "2026-01-16T09:56:03.180967+00:00"
  }
]